cycloplanning/__init__.py
cycloplanning/cli.py
cycloplanning-0.1.1.dist-info/METADATA
cycloplanning-0.1.1.dist-info/WHEEL
cycloplanning-0.1.1.dist-info/entry_points.txt
cycloplanning-0.1.1.dist-info/licenses/LICENSE
cycloplanning-0.1.1.dist-info/RECORD
